forecopy/__init__.py
forecopy/cov.py
forecopy/fun.py
forecopy/lsrec.py
forecopy/reco.py
forecopy/tools.py
forecopy-0.1.1.dist-info/licenses/LICENSE
forecopy-0.1.1.dist-info/METADATA
forecopy-0.1.1.dist-info/WHEEL
forecopy-0.1.1.dist-info/top_level.txt
forecopy-0.1.1.dist-info/RECORD
