Metadata-Version: 2.4
Name: forecopy
Version: 0.1.1
Summary: Forecast Reconciliation in Python
Author: Bohan Zhang
Author-email: Daniele Girolimetto <daniele.girolimetto@unipd.it>
Maintainer-email: Daniele Girolimetto <daniele.girolimetto@unipd.it>
License-Expression: MIT
Project-URL: homepage, https://danigiro.github.io/FoRecoPy/
Project-URL: documentation, https://danigiro.github.io/FoRecoPy/overview.html
Project-URL: source, https://github.com/danigiro/FoRecoPy
Project-URL: download, https://pypi.org/project/forecopy/#files
Project-URL: tracker, https://github.com/danigiro/forecopy/issues
Project-URL: changelog, https://danigiro.github.io/FoRecoPy/changelog.html
Project-URL: PyPI, https://pypi.org/project/forecopy
Keywords: forecasting,reconciliation,forecast,time-series
Classifier: Programming Language :: Python :: 3
Classifier: Operating System :: Microsoft :: Windows
Classifier: Operating System :: POSIX
Classifier: Operating System :: Unix
Classifier: Operating System :: MacOS
Requires-Python: >=3.10
License-File: LICENSE
Requires-Dist: numpy>=2.0.2
Requires-Dist: pandas>=2.2.2
Requires-Dist: scipy>=1.14.1
Requires-Dist: jax>=0.4.31
Requires-Dist: lineax>=0.0.8
Dynamic: license-file
